test_pkg_iaosid-0.1.0.dist-info/METADATA
test_pkg_iaosid-0.1.0.dist-info/WHEEL
test_pkg_iaosid/__init__.py
test_pkg_iaosid-0.1.0.dist-info/RECORD
