Metadata-Version: 2.1
Name: test-pkg-iaosid
Version: 0.1.0
Summary: test project
Author-Email: 29th-Day <43274844+29th-Day@users.noreply.github.com>
License: MIT
Requires-Python: >=3.12
